robot_opentmi/__init__.py
robot_opentmi/plugin.py
robot_opentmi-0.2.3.dist-info/METADATA
robot_opentmi-0.2.3.dist-info/WHEEL
robot_opentmi-0.2.3.dist-info/top_level.txt
robot_opentmi-0.2.3.dist-info/RECORD
