Metadata-Version: 2.1
Name: robot-opentmi
Version: 0.2.3
Summary: robot-framework plugin for publish results to opentmi
Home-page: https://github.com/opentmi/robot-opentmi
Author: Jussi Vatjus-Anttila
Author-email: jussiva@gmail.com
License: MIT
Keywords: robot-framework opentmi report
Platform: UNKNOWN
Classifier: Development Status :: 3 - Alpha
Classifier: Intended Audience :: Developers
Classifier: License :: OSI Approved :: MIT License
Classifier: Operating System :: POSIX
Classifier: Operating System :: Microsoft :: Windows
Classifier: Operating System :: MacOS :: MacOS X
Classifier: Framework :: Robot Framework :: Library
Classifier: Topic :: Software Development :: Quality Assurance
Classifier: Topic :: Software Development :: Testing
Classifier: Topic :: Utilities
Classifier: Programming Language :: Python
Classifier: Programming Language :: Python :: 3
Classifier: Programming Language :: Python :: 3.6
Classifier: Programming Language :: Python :: 3.7
Classifier: Programming Language :: Python :: 3 :: Only
Requires-Python: >=3.6
Requires-Dist: robotframework
Requires-Dist: opentmi-client (>=0.6.2)
Requires-Dist: joblib
Provides-Extra: dev
Requires-Dist: coverage ; extra == 'dev'
Requires-Dist: coveralls ; extra == 'dev'
Requires-Dist: mock ; extra == 'dev'
Requires-Dist: pylint ; extra == 'dev'
Requires-Dist: nose ; extra == 'dev'
Requires-Dist: pyinstaller ; extra == 'dev'
